airoot/base_model.py
airoot/test_load_model.py
airoot/audio/__init__.py
airoot/audio/audio_to_text.py
airoot/audio/text_to_audio.py
airoot/audio/xtts.py
airoot/bin/__init__.py
airoot/bin/audiogen.py
airoot/bin/audiototext.py
airoot/bin/imagegen.py
airoot/bin/textgen.py
airoot/bin/videogen.py
airoot/etc/__init__.py
airoot/image/__init__.py
airoot/image/image_to_text.py
airoot/image/text_to_image.py
airoot/text/__init__.py
airoot/text/llms.py
airoot/text/pdf_to_text.py
airoot/video/__init__.py
airoot/video/image_to_video.py
airoot/video/text_to_video.py
airoot/video/video_to_text.py
airoot-0.0.1.dist-info/METADATA
airoot-0.0.1.dist-info/WHEEL
airoot-0.0.1.dist-info/entry_points.txt
airoot-0.0.1.dist-info/top_level.txt
airoot-0.0.1.dist-info/RECORD
