Metadata-Version: 2.1
Name: airoot
Version: 0.0.1
Summary: Suite of generation models for text, image, audio and video.
Author-email: Ramya Kottapalli <rskottap@gmail.com>
Project-URL: source, https://github.com/rskottap/airoot
Project-URL: download, https://pypi.org/project/airoot/#files
Requires-Dist: python-magic
Requires-Dist: colorlog
Requires-Dist: torchsde
Requires-Dist: Pillow
Requires-Dist: transformers
Requires-Dist: accelerate
Requires-Dist: optimum
Requires-Dist: assure
Requires-Dist: mmry
Requires-Dist: diffusers[torch]
Requires-Dist: huggingface-hub[cli]
Provides-Extra: dev
Requires-Dist: pytest; extra == "dev"
Requires-Dist: twine; extra == "dev"
Requires-Dist: black; extra == "dev"
Requires-Dist: isort; extra == "dev"
Requires-Dist: pre-commit; extra == "dev"
